todopy2-1.3.dist-info/METADATA
todopy2-1.3.dist-info/RECORD
todopy2-1.3.dist-info/pydist.json
todopy2-1.3.dist-info/top_level.txt
todopy2-1.3.dist-info/DESCRIPTION.rst
todopy2-1.3.dist-info/WHEEL
todopy2-1.3.data/scripts/todo
todopy2/parser.py
todopy2/__init__.py
