Metadata-Version: 2.0
Name: todopy2
Version: 1.3
Summary: Simple to-do list CLI manager in Python
Home-page: https://github.com/kotnik/todopy2
Author: Nikola Kotur
Author-email: kotnick@gmail.com
License: GPLv3+
Platform: UNKNOWN
Classifier: Development Status :: 5 - Production/Stable
Classifier: Environment :: Console
Classifier: Intended Audience :: End Users/Desktop
Classifier: Natural Language :: English
Classifier: License :: OSI Approved :: GNU General Public License v3 or later (GPLv3+)
Classifier: Operating System :: OS Independent
Classifier: Programming Language :: Python
Classifier: Programming Language :: Python :: 2
Classifier: Programming Language :: Python :: 3
Classifier: Topic :: Office/Business :: Scheduling
